liwc/__init__.py
liwc/dic.py
liwc/trie.py
liwc-0.5.0.dist-info/LICENSE.txt
liwc-0.5.0.dist-info/METADATA
liwc-0.5.0.dist-info/WHEEL
liwc-0.5.0.dist-info/top_level.txt
liwc-0.5.0.dist-info/zip-safe
liwc-0.5.0.dist-info/RECORD
