Metadata-Version: 2.1
Name: liwc
Version: 0.5.0
Summary: Linguistic Inquiry and Word Count (LIWC) analyzer (proprietary data not included)
Home-page: https://github.com/chbrown/liwc-python
Author: Christopher Brown
Author-email: chrisbrown@utexas.edu
License: MIT
Platform: UNKNOWN
